Metadata-Version: 2.1
Name: topsis-vansh-102303137
Version: 1.0.1
Summary: TOPSIS implementation for MCDM problems
Author: Vansh Garg
Author-email: your_email@gmail.com
Requires-Dist: numpy
Requires-Dist: pandas
